[
  {"id":"S360-01","dimension":"病史采集与血尿定位","max":50,"coreRequirements":"确认真性血尿，覆盖起病、时相、颜色、血块、疼痛和伴随症状","excellentPerformance":"问题聚焦、追问有层次且不诱导","deductionPoints":"定位线索缺失或问题重复","scoringAdvice":"以对话槽位和时间线为证据"},
  {"id":"S360-02","dimension":"危险因素和安全网","max":40,"coreRequirements":"覆盖肿瘤、感染、肾小球、抗栓、妇科污染和全身出血安全网","excellentPerformance":"能按病例风险主动排查严重病因","deductionPoints":"把抗栓药作为唯一解释或漏高危线索","scoringAdvice":"按病例特异严重错误规则扣分"},
  {"id":"S360-03","dimension":"查体与急症识别","max":35,"coreRequirements":"选择针对性查体并识别休克、脓毒症、尿潴留、AKI和外伤","excellentPerformance":"先稳定患者再推进检查","deductionPoints":"漏生命体征或急症处理顺序错误","scoringAdvice":"使用查体日志和阶段顺序"},
  {"id":"S360-04","dimension":"诊断与鉴别诊断","max":45,"coreRequirements":"最可能诊断、依据、至少3项鉴别及支持/反对点","excellentPerformance":"定位清楚并说明确认检查","deductionPoints":"单一诊断或遗漏高危鉴别","scoringAdvice":"以诊断阶段提交为证据"},
  {"id":"S360-05","dimension":"检验、影像、内镜及病理决策","max":55,"coreRequirements":"选择必要项目、满足前置条件并避免重复过度检查","excellentPerformance":"开单顺序合理且说明目的","deductionPoints":"关键漏检、重复开单、过度检查或引用未开结果","scoringAdvice":"使用结构化医嘱日志"},
  {"id":"S360-06","dimension":"MDT与会诊","max":45,"coreRequirements":"填写科室、触发原因、问题、证据和汇报摘要","excellentPerformance":"时机正确、问题聚焦且科室匹配","deductionPoints":"只勾科室或漏必须会诊","scoringAdvice":"按MDT触发规则和申请文本评分"},
  {"id":"S360-07","dimension":"治疗及围术期管理","max":50,"coreRequirements":"区分即时、病因、确定性和围术期管理","excellentPerformance":"顺序安全并覆盖抗栓、感染、麻醉、VTE和ERAS","deductionPoints":"触发病例严重错误","scoringAdvice":"治疗和围术期合并为50分"},
  {"id":"S360-08","dimension":"随访、教育和表达效率","max":40,"coreRequirements":"给出复查项目、时点、警示症状和教育，表达清晰","excellentPerformance":"计划可执行且资源使用有效率","deductionPoints":"无随访时点、无升级就诊条件或重复操作过多","scoringAdvice":"结合完整时间线评分"}
]
